{"cameraMode":{"drawMode":0,"name":"Shaded","section":"Shading Mode"},"sceneLighting":true,"audioPlay":false,"sceneViewState":{"m_AlwaysRefresh":false,"showFog":true,"showSkybox":true,"showFlares":true,"showImageEffects":true,"showParticleSystems":true,"showVisualEffectGraphs":true,"m_FxEnabled":true},"in2DMode":false,"pivot":{"x":6.37178373336792,"y":2.84220290184021,"z":-15.256388664245606},"rotation":{"x":-0.1332266628742218,"y":0.8659319877624512,"z":-0.3608236014842987,"w":-0.3197243809700012},"size":5.701769828796387,"orthographic":false}